{
  "tabId": "T-004",
  "name": "Predmet pregleda",
  "description": "Inspection field type selection",
  "phase": "introduction",
  "globalVariablesSet": [
    "HG-INSPECTION_FIELD_ID",
    "HG-INSPECTION_FIELD_TYPE",
    "HG-RULE_COUNT"
  ],
  "globalVariablesRequired": [],
  "localVariables": [],
  "entityMapping": {
    "entity": "InspectionField",
    "mode": "select_one"
  },
  "sections": [
    {
      "id": "S-1",
      "title": "Izbira področja pregleda",
      "description": "Select the type of inspection to perform",
      "fields": [
        {
          "id": "fieldSelection",
          "label": "Področje pregleda",
          "type": "card-selector",
          "required": true,
          "dataSource": {
            "entity": "InspectionField",
            "filter": ["=", "@item.isActive", true],
            "displayFields": ["name", "description", "ruleCount"],
            "cardTemplate": {
              "title": "@item.name",
              "subtitle": "@item.description",
              "badge": {
                "text": ["str/concat", "@item.ruleCount", " pravil"],
                "variant": "info"
              }
            }
          },
          "hiddenCalculations": [
            {
              "variable": "HG-INSPECTION_FIELD_ID",
              "expression": "@payload.value.id",
              "scope": "global"
            },
            {
              "variable": "HG-INSPECTION_FIELD_TYPE",
              "expression": "@payload.value.fieldType",
              "scope": "global"
            },
            {
              "variable": "HG-RULE_COUNT",
              "expression": "@payload.value.ruleCount",
              "scope": "global"
            }
          ]
        }
      ]
    },
    {
      "id": "S-2",
      "title": "Povzetek",
      "description": "Summary of selected inspection field",
      "condition": ["!=", "@entity.globalVariables.HG_INSPECTION_FIELD_ID", null],
      "fields": [
        {
          "id": "summary",
          "label": "Izbrano področje",
          "type": "info-display",
          "displayTemplate": {
            "title": "Pregled: @entity.globalVariables.HG_INSPECTION_FIELD_TYPE",
            "content": "Število pravil za preverjanje: @entity.globalVariables.HG_RULE_COUNT"
          }
        }
      ]
    }
  ],
  "validationRules": [
    {
      "condition": ["!=", "@entity.globalVariables.HG_INSPECTION_FIELD_ID", null],
      "message": "Izbira področja pregleda je obvezna"
    }
  ]
}
